dbt_sugar/__init__.py
dbt_sugar/core/__init__.py
dbt_sugar/core/_version.py
dbt_sugar/core/clients/__init__.py
dbt_sugar/core/clients/dbt.py
dbt_sugar/core/clients/yaml_helpers.py
dbt_sugar/core/config/__init__.py
dbt_sugar/core/config/config.py
dbt_sugar/core/connectors/base.py
dbt_sugar/core/connectors/postgres_connector.py
dbt_sugar/core/connectors/redshift_connector.py
dbt_sugar/core/connectors/snowflake_connector.py
dbt_sugar/core/exceptions.py
dbt_sugar/core/flags.py
dbt_sugar/core/logger.py
dbt_sugar/core/main.py
dbt_sugar/core/task/__init__.py
dbt_sugar/core/task/audit.py
dbt_sugar/core/task/base.py
dbt_sugar/core/task/bootstrap.py
dbt_sugar/core/task/doc.py
dbt_sugar/core/ui/__init__.py
dbt_sugar/core/ui/cli_ui.py
dbt_sugar/core/ui/traceback_manager.py
dbt_sugar/core/utils.py
dbt_sugar-0.2.0.dist-info/entry_points.txt
dbt_sugar-0.2.0.dist-info/LICENSE
dbt_sugar-0.2.0.dist-info/WHEEL
dbt_sugar-0.2.0.dist-info/METADATA
dbt_sugar-0.2.0.dist-info/RECORD
