Metadata-Version: 2.1
Name: dbt-sugar
Version: 0.2.0
Summary: A sweet CLI tool to help dbt users enforce documentation and testing on their dbt projects.
Home-page: https://github.com/bitpicky/dbt-sugar
License: GPLv3+
Keywords: data engineering,dbt,ETL,data modelling
Author: Bastien Boutonnet
Author-email: bastien.b1@gmail.com
Requires-Python: >=3.6.3,<4.0
Classifier: Development Status :: 3 - Alpha
Classifier: Intended Audience :: Developers
Classifier: License :: OSI Approved :: MIT License
Classifier: License :: Other/Proprietary License
Classifier: Programming Language :: Python :: 3
Classifier: Programming Language :: Python :: 3.10
Classifier: Programming Language :: Python :: 3.6
Classifier: Programming Language :: Python :: 3.7
Classifier: Programming Language :: Python :: 3.8
Classifier: Programming Language :: Python :: 3.9
Classifier: Topic :: Software Development :: Build Tools
Requires-Dist: PyYAML (>=5.4.1,<6.0.0)
Requires-Dist: SQLAlchemy (>=1.3.0,<1.5.0)
Requires-Dist: click (>=7.1.2,<8.0.0)
Requires-Dist: logredactor (>=0.0.1,<0.0.2)
Requires-Dist: luddite (>=1.0.1,<2.0.0)
Requires-Dist: packaging (>=20.8,<22.0)
Requires-Dist: pretty-errors (>=1.2.19,<2.0.0)
Requires-Dist: psycopg2 (>=2.8.6,<3.0.0)
Requires-Dist: pydantic (>=1.8,<2.0)
Requires-Dist: pyfiglet (>=0.8.post1,<0.9)
Requires-Dist: questionary (>=1.9.0,<2.0.0)
Requires-Dist: rich (>=9.13,<11.0)
Requires-Dist: ruamel.yaml (>=0.17.10,<0.18.0)
Requires-Dist: snowflake-sqlalchemy (==1.2.4)
Requires-Dist: sqlalchemy-redshift (>=0.8.2,<0.9.0)
Requires-Dist: yamlloader (>=1.0.0,<2.0.0)
Project-URL: Documentation, https://bitpicky.gitbook.io/dbt-sugar/
Project-URL: Repository, https://github.com/bitpicky/dbt-sugar
